chessanalytics_st/__init__.py
chessanalytics_st/chessanalytics_st.py
chessanalytics_st-0.3.0.dist-info/LICENSE
chessanalytics_st-0.3.0.dist-info/METADATA
chessanalytics_st-0.3.0.dist-info/WHEEL
chessanalytics_st-0.3.0.dist-info/top_level.txt
chessanalytics_st-0.3.0.dist-info/RECORD
