Metadata-Version: 2.1
Name: chessanalytics-st
Version: 0.3.0
Summary: Graphical representation of functions from chessanalytics library designed for Streamlit apps.
Home-page: https://github.com/lot022/chessanalytics_st
Author: lot022
Classifier: Programming Language :: Python :: 3
Classifier: License :: OSI Approved :: MIT License
Classifier: Operating System :: OS Independent
Requires-Python: >=3.7
License-File: LICENSE
Requires-Dist: numpy
Requires-Dist: streamlit
Requires-Dist: pandas
Requires-Dist: plotly
Requires-Dist: chessanalytics
